siglent_scpi/__init__.py
siglent_scpi/sdg.py
siglent_scpi/sds.py
siglent_scpi/siglent.py
siglent_scpi-1.0.3.dist-info/METADATA
siglent_scpi-1.0.3.dist-info/WHEEL
siglent_scpi-1.0.3.dist-info/licenses/LICENSE
siglent_scpi-1.0.3.dist-info/RECORD
