Metadata-Version: 2.3
Name: siglent_scpi
Version: 1.0.3
Summary: A package to automate Siglent equipment
Author-email: kvdijken <sla_nippers_0x@icloud.com>
License-File: LICENSE
Classifier: License :: OSI Approved :: MIT License
Classifier: Operating System :: OS Independent
Classifier: Programming Language :: Python :: 3
Requires-Python: >=3.11
Requires-Dist: numpy
Requires-Dist: scipy
Provides-Extra: thd
Requires-Dist: matplotlib; extra == 'thd'
